goodgame/__init__.py
goodgame/app.py
goodgame/audio.py
goodgame/bmf.py
goodgame/clock.py
goodgame/cursor.py
goodgame/events.py
goodgame/exceptions.py
goodgame/gamecontroller.py
goodgame/joystick.py
goodgame/loader.py
goodgame/math.py
goodgame/mixer.py
goodgame/numba.py
goodgame/opengl.py
goodgame/renderer.py
goodgame/sdl.py
goodgame/sdlgfx.py
goodgame/sensor.py
goodgame/surface.py
goodgame/texture.py
goodgame/touch.py
goodgame/ttf.py
goodgame/video.py
goodgame/window.py
goodgame-0.2.0.dist-info/LICENSE.md
goodgame-0.2.0.dist-info/METADATA
goodgame-0.2.0.dist-info/WHEEL
goodgame-0.2.0.dist-info/top_level.txt
goodgame-0.2.0.dist-info/zip-safe
goodgame-0.2.0.dist-info/RECORD
