Metadata-Version: 2.1
Name: goodgame
Version: 0.2.0
Summary: A simple and nice pysdl2 wrapper.
Home-page: https://github.com/Pyxelsuft/goodgame
Author: Pixelsuft
License: MIT
Project-URL: Readme, https://github.com/Pyxelsuft/goodgame/blob/main/README.md
Project-URL: Documentation, https://github.com/Pyxelsuft/goodgame/tree/main/docs
Project-URL: Issue tracker, https://github.com/Pyxelsuft/goodgame/issues
Keywords: goodgame
Classifier: License :: OSI Approved :: MIT License
Classifier: Topic :: Games/Entertainment
Classifier: Topic :: Multimedia
Classifier: Topic :: Software Development
Classifier: Operating System :: Android
Classifier: Operating System :: MacOS
Classifier: Operating System :: Microsoft :: Windows
Classifier: Operating System :: POSIX
Classifier: Operating System :: Unix
Classifier: Operating System :: iOS
Classifier: Programming Language :: Python :: 3
Classifier: Programming Language :: Python :: 3.6
Classifier: Programming Language :: Python :: 3.7
Classifier: Programming Language :: Python :: 3.8
Classifier: Programming Language :: Python :: 3.9
Classifier: Programming Language :: Python :: 3.10
Classifier: Programming Language :: Python :: 3.11
Classifier: Programming Language :: Python :: 3.12
Requires-Python: >=3.6
License-File: LICENSE.md
Requires-Dist: pysdl2
